bbrl_gymnasium/__init__.py
bbrl_gymnasium/_version.py
bbrl_gymnasium/envs/__init__.py
bbrl_gymnasium/envs/continuous_2D_mdp.py
bbrl_gymnasium/envs/continuous_cartpole.py
bbrl_gymnasium/envs/continuous_line_mdp.py
bbrl_gymnasium/envs/debug_env.py
bbrl_gymnasium/envs/line_mdp.py
bbrl_gymnasium/envs/maze_mdp.py
bbrl_gymnasium/envs/rocket_lander.py
bbrl_gymnasium-2.0.0.dist-info/LICENSE
bbrl_gymnasium-2.0.0.dist-info/METADATA
bbrl_gymnasium-2.0.0.dist-info/WHEEL
bbrl_gymnasium-2.0.0.dist-info/top_level.txt
bbrl_gymnasium-2.0.0.dist-info/RECORD
