Metadata-Version: 2.1
Name: bbrl-gymnasium
Version: 2.0.0
Summary: A set of additional gym environments
Home-page: https://github.com/osigaud/my_gym
Author: Olivier Sigaud
Author-email: Olivier.Sigaud@isir.upmc.fr
License: MIT
Platform: UNKNOWN
License-File: LICENSE
Requires-Dist: numpy (>=1.19.1)
Requires-Dist: gymnasium (~=0.27)
Requires-Dist: swig
Requires-Dist: box2d-py
Requires-Dist: mazemdp (>=0.7.3)
